mill_local/__init__.py
mill_local-0.5.0.dist-info/licenses/LICENSE
mill_local-0.5.0.dist-info/METADATA
mill_local-0.5.0.dist-info/WHEEL
mill_local-0.5.0.dist-info/top_level.txt
mill_local-0.5.0.dist-info/RECORD
