Metadata-Version: 2.4
Name: mill_local
Version: 0.5.0
Summary: A python3 library to communicate with Mill heaters using local Gen 3 API
Home-page: https://github.com/Danielhiversen/pyMillLocal
Author: Daniel Hjelseth Høyer
Author-email: mail@dahoiv.net
License: MIT
Classifier: Intended Audience :: Developers
Classifier: Operating System :: OS Independent
Classifier: Programming Language :: Python
Classifier: Programming Language :: Python :: 3
Classifier: Topic :: Software Development :: Libraries :: Python Modules
Requires-Python: >=3.8.0
License-File: LICENSE
Requires-Dist: aiohttp
Requires-Dist: async_timeout
Dynamic: author
Dynamic: author-email
Dynamic: classifier
Dynamic: home-page
Dynamic: license
Dynamic: license-file
Dynamic: requires-dist
Dynamic: requires-python
Dynamic: summary
